{"address":"0x06f3CDabae564B0546529b4DD8FeF1bcD4235753","category":"token","date_added":"2020-04-02T00:00:00.000Z","description":"Launched on 23/03/2020 by a team based in Russia, Switzerland, and Liechtenstein, TILWIKI is a global art and antique art blockchain platform that enables users to sell and buy art online including tokenized art through Artsharing (fractional ownership) to remove restrictive barriers preventing investor access. The solution claims to be the first to provide BigData spanning museums and galleries in 199 countries while also serving as an education and learning hub.","id":5399,"links":{"explorer":["https://etherscan.io/token/0x06f3cdabae564b0546529b4dd8fef1bcd4235753","https://ethplorer.io/address/0x06f3cdabae564b0546529b4dd8fef1bcd4235753"],"message_board":["https://tilwiki.com/blog/9-tlw-is-on-exchange-"],"reddit":["https://reddit.com/r/tilwiki_official"],"technical_doc":["https://tilwiki.com/upload/about/tilwiki_memorandum.pdf"],"twitter":["https://twitter.com/TILWIKI1"],"website":["https://tilwiki.com"]},"markets":[{"base":{"currency_id":5399,"currency_symbol":"TLW","currency_type":"cryptocurrency","exchange_symbol":"TLW"},"exchange_id":477,"exchange_name":"ProBit Exchange","pair":"TLW/BTC","quote":{"currency_id":1,"currency_symbol":"BTC","currency_type":"cryptocurrency","exchange_symbol":"BTC"},"url":"https://www.probit.com/app/exchange/TLW-BTC"},{"base":{"currency_id":5399,"currency_symbol":"TLW","currency_type":"cryptocurrency","exchange_symbol":"TLW"},"exchange_id":477,"exchange_name":"ProBit Exchange","pair":"TLW/USDT","quote":{"currency_id":825,"currency_symbol":"USDT","currency_type":"cryptocurrency","exchange_symbol":"USDT"},"url":"https://www.probit.com/app/exchange/TLW-USDT"}],"name":"TILWIKI","rank":2610,"slug":"tilwiki","status":"active","symbol":"TLW"}