{"address":"0x16c1E5BAF21b9Fa4BC9f2C374E4dC19fAB5Ac5Dc","id":3579,"links":{"Announcement":"https://bitcointalk.org/index.php?topic=5059749.0","Chat":"https://t.me/joinchat/I6B4d08SYQeNJQizFixY7g","Chat 2":"https://open.kakao.com/o/g3m71BZ","Explorer":"https://etherscan.io/token/0x16c1e5baf21b9fa4bc9f2c374e4dc19fab5ac5dc","Explorer 2":"https://etherscan.io/address/0x16c1e5baf21b9fa4bc9f2c374e4dc19fab5ac5dc","Message Board":"https://medium.com/@Allbit","Technical Documentation":"https://apot.io/guide/APOT_White%20paper_v.0.9.3._181031.pdf","Website":"https://allbit.com/","Website 2":"https://apot.io/"},"markets":[{"exchange_name":"Allbit","pair":"APOT/BTC","url":"https://allbit.com/exchange/APOT"},{"exchange_name":"Allbit","pair":"APOT/ETH","url":"https://allbit.com/exchange/APOT"},{"exchange_name":"Allbit","pair":"CNUS/APOT","url":"https://allbit.com/exchange/CNUS"},{"exchange_name":"Allbit","pair":"IOTX/APOT","url":"https://allbit.com/exchange/IOTX"},{"exchange_name":"Allbit","pair":"PIB/APOT","url":"https://allbit.com/exchange/PIB"},{"exchange_name":"Allbit","pair":"VNT/APOT","url":"https://allbit.com/exchange/VNT"},{"exchange_name":"Cashierest","pair":"APOT/KRW","url":"https://www.cashierest.com/Stock/CoinStock"}],"name":"APOT","rank":2188,"symbol":"APOT","tags":["Token"],"website_slug":"apot"}