{"address":"0x1E26b3D07E57F453caE30F7DDd2f945f5bF3EF33","id":2622,"links":{"Announcement":"https://bitcointalk.org/index.php?topic=2710499","Chat":"https://t.me/clearcoin","Explorer":"https://etherscan.io/token/0x1E26b3D07E57F453caE30F7DDd2f945f5bF3EF33","Explorer 2":"https://etherscan.io/token/0x1E26b3D07E57F453caE30F7DDd2f945f5bF3EF33","Message Board":"https://clearcoin.co/blog/","Reddit":"https://www.reddit.com/r/clearcoin","Source Code":"https://github.com/clearcoin","Technical Documentation":"https://clearcoin.co/whitepaper/","Twitter":"https://twitter.com/clearcoinhq","Website":"https://clearcoin.co/"},"markets":[{"exchange_name":"HitBTC","pair":"XCLR/BTC","url":"https://hitbtc.com/XCLR-to-BTC"}],"name":"ClearCoin","rank":1528,"symbol":"XCLR","tags":["Token"],"website_slug":"clearcoin"}