{"address":"0x2ecB13A8c458c379c4d9a7259e202De03c8F3D19","category":"token","date_added":"2018-10-11T00:00:00.000Z","id":3406,"links":{"chat":["https://t.me/BCtoken"],"explorer":["https://etherscan.io/token/0x2ecb13a8c458c379c4d9a7259e202de03c8f3d19","https://ethplorer.io/address/0x2ecb13a8c458c379c4d9a7259e202de03c8f3d19"],"twitter":["https://twitter.com/Block_Chain_com"],"website":["https://block-chain.com","https://ico.block-chain.com/"]},"markets":[{"base":{"currency_id":3406,"currency_symbol":"BC","currency_type":"cryptocurrency","exchange_symbol":"BC"},"exchange_id":382,"exchange_name":"Crex24","pair":"BC/BTC","quote":{"currency_id":1,"currency_symbol":"BTC","currency_type":"cryptocurrency","exchange_symbol":"BTC"},"url":"https://crex24.com/exchange/BC-BTC"}],"name":"Block-Chain.com","rank":927,"slug":"block-chain-com","status":"active","symbol":"BC"}