{"address":"0x301C755bA0fcA00B1923768Fffb3Df7f4E63aF31","category":"token","date_added":"2019-09-25T00:00:00.000Z","description":"Global Digital Content (GDC) is the new utility token for millennials to consume digital content from media, commerce, entertainment, game and wallet with the services we are developing and partnering around the globe.","id":4678,"links":{"announcement":["https://medium.com/@globaldigitalcontent"],"chat":["https://t.me/joinchat/Jp00JUWbfXk3fHB4CR0l_w"],"explorer":["https://etherscan.io/token/0x301C755bA0fcA00B1923768Fffb3Df7f4E63aF31","https://ethplorer.io/address/0x301C755bA0fcA00B1923768Fffb3Df7f4E63aF31"],"message_board":["https://medium.com/@globaldigitalcontent","https://www.facebook.com/GlobalDigitalContent/"],"reddit":["https://reddit.com/r/rankingball"],"source_code":["https://github.com/gdctoken/gdctoken"],"technical_doc":["https://drive.google.com/file/d/1bdcXaYVSxEIDzGix9vI337Eu0F-hqec3/view"],"twitter":["https://twitter.com/GDC__Global"],"website":["http://gdctoken.io/"]},"markets":[{"base":{"currency_id":4678,"currency_symbol":"GDC","currency_type":"cryptocurrency","exchange_symbol":"GDC"},"exchange_id":489,"exchange_name":"Bithumb Global","pair":"GDC/BTC","quote":{"currency_id":1,"currency_symbol":"BTC","currency_type":"cryptocurrency","exchange_symbol":"BTC"},"url":"https://www.bithumb.pro/en-us/spot/trade;symbol=GDC_BTC"},{"base":{"currency_id":4678,"currency_symbol":"GDC","currency_type":"cryptocurrency","exchange_symbol":"GDC"},"exchange_id":343,"exchange_name":"CoinBene","pair":"GDC/ETH","quote":{"currency_id":1027,"currency_symbol":"ETH","currency_type":"cryptocurrency","exchange_symbol":"ETH"},"url":"https://www.coinbene.com/exchange.html#/exchange?pairId=GDCETH?hash=2NbmTq6"},{"base":{"currency_id":4678,"currency_symbol":"GDC","currency_type":"cryptocurrency","exchange_symbol":"GDC"},"exchange_id":343,"exchange_name":"CoinBene","pair":"GDC/USDT","quote":{"currency_id":825,"currency_symbol":"USDT","currency_type":"cryptocurrency","exchange_symbol":"USDT"},"url":"https://www.coinbene.com/exchange.html#/exchange?pairId=GDCUSDT?hash=2NbmTq6"},{"base":{"currency_id":4678,"currency_symbol":"GDC","currency_type":"cryptocurrency","exchange_symbol":"GDC"},"exchange_id":343,"exchange_name":"CoinBene","pair":"GDC/BTC","quote":{"currency_id":1,"currency_symbol":"BTC","currency_type":"cryptocurrency","exchange_symbol":"BTC"},"url":"https://www.coinbene.com/exchange.html#/exchange?pairId=GDCBTC?hash=2NbmTq6"},{"base":{"currency_id":4678,"currency_symbol":"GDC","currency_type":"cryptocurrency","exchange_symbol":"GDC"},"exchange_id":404,"exchange_name":"Kyber Network","pair":"GDC/ETH","quote":{"currency_id":1027,"currency_symbol":"ETH","currency_type":"cryptocurrency","exchange_symbol":"ETH"},"url":"https://kyberswap.com/swap/gdc-eth"}],"name":"Global Digital Content","rank":802,"slug":"global-digital-content","status":"active","symbol":"GDC"}