{"address":"0x340D2bdE5Eb28c1eed91B2f790723E3B160613B7","id":2223,"links":{"Announcement":"https://bitcointalk.org/index.php?topic=2181569.0","Chat":"https://t.me/block_v","Explorer":"https://etherscan.io/token/0x340d2bde5eb28c1eed91b2f790723e3b160613b7","Explorer 2":"https://ethplorer.io/address/0x340d2bde5eb28c1eed91b2f790723e3b160613b7","Message Board":"https://medium.com/@blockv_io","Reddit":"https://www.reddit.com/r/blockv","Source Code":"https://github.com/BLOCKvIO/documentation","Technical Documentation":"https://blockv.io/documents/whitepaper.pdf","Twitter":"https://twitter.com/blockv_io","Website":"https://blockv.io/"},"markets":[{"exchange_name":"Bancor Network","pair":"VEE/BNT","url":"https://www.bancor.network/token/VEE"},{"exchange_name":"Bittrex","pair":"VEE/BTC","url":"https://bittrex.com/Market/Index?MarketName=BTC-VEE"},{"exchange_name":"Ethfinex","pair":"VEE/BTC","url":"https://www.ethfinex.com/"},{"exchange_name":"Ethfinex","pair":"VEE/ETH","url":"https://www.ethfinex.com/"},{"exchange_name":"Ethfinex","pair":"VEE/USD","url":"https://www.ethfinex.com/"},{"exchange_name":"IDEX","pair":"VEE/ETH","url":"https://idex.market/eth/vee"},{"exchange_name":"Tidex","pair":"VEE/BTC","url":"https://tidex.com/#/exchange/VEE_BTC"},{"exchange_name":"Tidex","pair":"VEE/ETH","url":"https://tidex.com/#/exchange/VEE_ETH"},{"exchange_name":"Upbit","pair":"VEE/BTC","url":"https://upbit.com/exchange?code=CRIX.UPBIT.BTC-VEE"}],"name":"BLOCKv","rank":346,"symbol":"VEE","tags":["Token"],"website_slug":"blockv"}