{"address":"0x445f51299Ef3307dBD75036dd896565F5B4BF7A5","category":"token","date_added":"2019-04-05T00:00:00.000Z","description":"V-ID secures digital files against unlawful manipulation The VIDT API enables organizations to certify and secure their digital data against fraud and manipulation. It aims to protect value at minimum expense and effort. V-ID works with organizations like AmSpec, IBM, and Nyenrode University to certify and secure digital documents like certificates, invoices, diplomas, and sensor-data.","id":3845,"links":{"announcement":["https://bitcointalk.org/index.php?topic=4918204"],"chat":["https://t.me/vidtoken"],"explorer":["https://etherscan.io/token/0x445f51299ef3307dbd75036dd896565f5b4bf7a5","https://ethplorer.io/address/0x445f51299ef3307dbd75036dd896565f5b4bf7a5"],"message_board":["https://medium.com/@pim_vee/the-3rd-largest-criminal-activity-is-rapidly-digitizing-but-blockchain-can-fix-it-d3b03f721db6"],"reddit":["https://reddit.com/r/VIDT"],"source_code":["https://github.com/V-ID/V-ID-Token"],"technical_doc":["https://token.v-id.org/whitepaper"],"twitter":["https://twitter.com/v_id_blockchain"],"website":["https://about.v-id.org"]},"markets":[{"base":{"currency_id":3845,"currency_symbol":"VIDT","currency_type":"cryptocurrency","exchange_symbol":"VIDT"},"exchange_id":311,"exchange_name":"KuCoin","pair":"VIDT/BTC","quote":{"currency_id":1,"currency_symbol":"BTC","currency_type":"cryptocurrency","exchange_symbol":"BTC"},"url":"https://www.kucoin.com/trade/VIDT-BTC"},{"base":{"currency_id":3845,"currency_symbol":"VIDT","currency_type":"cryptocurrency","exchange_symbol":"VIDT"},"exchange_id":310,"exchange_name":"IDEX","pair":"VIDT/ETH","quote":{"currency_id":1027,"currency_symbol":"ETH","currency_type":"cryptocurrency","exchange_symbol":"ETH"},"url":"https://idex.market/eth/vidt"},{"base":{"currency_id":3845,"currency_symbol":"VIDT","currency_type":"cryptocurrency","exchange_symbol":"VIDT"},"exchange_id":400,"exchange_name":"Hotbit","pair":"VIDT/BTC","quote":{"currency_id":1,"currency_symbol":"BTC","currency_type":"cryptocurrency","exchange_symbol":"BTC"},"url":"https://www.hotbit.io/exchange?symbol=VIDT_BTC"},{"base":{"currency_id":3845,"currency_symbol":"VIDT","currency_type":"cryptocurrency","exchange_symbol":"VIDT-F53"},"exchange_id":486,"exchange_name":"Binance DEX","pair":"VIDT/BNB","quote":{"currency_id":1839,"currency_symbol":"BNB","currency_type":"cryptocurrency","exchange_symbol":"BNB"},"url":"https://www.binance.org/en/trade/VIDT-F53_BNB"},{"base":{"currency_id":3845,"currency_symbol":"VIDT","currency_type":"cryptocurrency","exchange_symbol":"VIDT"},"exchange_id":363,"exchange_name":"Fatbtc","pair":"VIDT/ETH","quote":{"currency_id":1027,"currency_symbol":"ETH","currency_type":"cryptocurrency","exchange_symbol":"ETH"},"url":"https://www.fatbtc.com/"}],"name":"V-ID","rank":483,"slug":"v-id","status":"active","symbol":"VIDT"}