{"address":"0x4D8fc1453a0F359e99c9675954e656D80d996FbF","id":2557,"links":{"Chat":"https://t.me/beetoken","Explorer":"https://etherscan.io/token/0x4d8fc1453a0f359e99c9675954e656d80d996fbf","Explorer 2":"https://ethplorer.io/address/0x4d8fc1453a0f359e99c9675954e656d80d996fbf","Message Board":"https://medium.com/@thebeetoken","Reddit":"https://www.reddit.com/r/beetoken","Source Code":"https://github.com/thebeetoken/","Technical Documentation":"https://s3-us-west-2.amazonaws.com/beenest-public/whitepaper/bee_whitepaper_v3.pdf","Twitter":"https://twitter.com/thebeetoken","Website":"https://www.beetoken.com/"},"markets":[{"exchange_name":"ABCC","pair":"BEE/BTC","url":"https://abcc.com/markets/beebtc"},{"exchange_name":"Bitrue","pair":"BEE/BTC","url":"https://www.bitrue.com/trade/bee_btc"},{"exchange_name":"Bitrue","pair":"BEE/XRP","url":"https://www.bitrue.com/trade/bee_xrp"},{"exchange_name":"IDEX","pair":"BEE/ETH","url":"https://idex.market/eth/bee"}],"name":"Bee Token","rank":1028,"symbol":"BEE","tags":["Token"],"website_slug":"bee-token"}