{"address":"0x514910771AF9Ca656af840dff83E8264EcF986CA","category":"token","date_added":"2017-09-20T00:00:00.000Z","description":"### What Is Chainlink?\nChainlink (LINK) is a decentralized oracle network which aims to connect smart contracts with data from the real world. Chainlink was developed by Sergey Nazarov, with Steve Ellis as the other co-founder. It held an ICO in September 2017, raising $32 million, with a total supply of 1 billion LINK tokens.\nLINK, the cryptocurrency native to the Chainlink decentralized oracle network, is used to pay node operators. Since the Chainlink network has a reputation system, node providers that have a large amount of LINK can be rewarded with larger contracts, while a failure to deliver accurate information results in a deduction of tokens. Developers describe LINK as \u201can ERC20 token, with the additional ERC223 'transfer and call' functionality of transfer (address, uint256, bytes), allowing tokens to be received and processed by contracts within a single transaction.\u201d Following the 2017 $32 million LINK ICO, 32 percent of LINK tokens were sent to node operators to incentivize the ecosystem and 30 percent stayed within Chainlink for development (35 percent were sold in the public token sale).\n\n### What Are Oracles?\nChainlink is a platform that aims to bridge the gap between blockchain technology-based smart contracts (made widespread by Ethereum), and real world applications. Since blockchains cannot access data outside their network, oracles (a defi instrument) are needed to function as data feeds in smart contracts. In Chainlink's case, the oracles are connected to the Ethereum network. Oracles provide external data (e.g. temperature, weather) that trigger smart contract executions upon the fulfillment of predefined conditions. Participants on the Chainlink network are incentivized (through rewards) to provide smart contracts with access to external data feeds like API information. Should users desire access to off-chain data, they can submit a requesting contract to Chainlink\u2019s network. These contracts will match the requesting contract with the appropriate oracles. The contracts include a reputation contract, an order-matching contract and an aggregating contract. The aggregating contract gathers data of the selected oracles to find the most accurate result.\n \n### Where Can You Buy Chainlink?\nYou can buy Chainlink (LINK) on any exchange that supports the digital currency. For the latest list of exchanges and trading pairs for this cryptocurrency, click on our [market pairs tab](https://coinmarketcap.com/currencies/chainlink/markets/).","id":1975,"links":{"explorer":["https://etherscan.io/token/0x514910771af9ca656af840dff83e8264ecf986ca","https://ethplorer.io/address/0x514910771af9ca656af840dff83e8264ecf986ca","https://blockchair.com/ethereum/erc-20/token/0x514910771af9ca656af840dff83e8264ecf986ca","https://eth.tokenview.com/en/token/0x514910771af9ca656af840dff83e8264ecf986ca"],"message_board":["https://medium.com/chainlink","https://blog.chain.link/"],"reddit":["https://reddit.com/r/chainlink"],"source_code":["https://github.com/smartcontractkit/chainlink"],"technical_doc":["https://link.smartcontract.com/whitepaper"],"twitter":["https://twitter.com/smart_contract"],"website":["https://chain.link/","https://smartcontract.com/"]},"markets":[{"base":{"currency_id":1975,"currency_symbol":"LINK","currency_type":"cryptocurrency","exchange_symbol":"LINK"},"exchange_id":656,"exchange_name":"Omgfin","pair":"LINK/BTC","quote":{"currency_id":1,"currency_symbol":"BTC","currency_type":"cryptocurrency","exchange_symbol":"BTC"},"url":"https://omgfin.com/exchange/trade/market/LINKBTC"},{"base":{"currency_id":1975,"currency_symbol":"LINK","currency_type":"cryptocurrency","exchange_symbol":"LINK"},"exchange_id":656,"exchange_name":"Omgfin","pair":"LINK/USDT","quote":{"currency_id":825,"currency_symbol":"USDT","currency_type":"cryptocurrency","exchange_symbol":"USDT"},"url":"https://omgfin.com/exchange/trade/market/LINKUSDT"},{"base":{"currency_id":1975,"currency_symbol":"LINK","currency_type":"cryptocurrency","exchange_symbol":"LINK"},"exchange_id":403,"exchange_name":"BitForex","pair":"LINK/BTC","quote":{"currency_id":1,"currency_symbol":"BTC","currency_type":"cryptocurrency","exchange_symbol":"BTC"},"url":"https://www.bitforex.com/en/spot/link_btc"},{"base":{"currency_id":1975,"currency_symbol":"LINK","currency_type":"cryptocurrency","exchange_symbol":"LINK"},"exchange_id":270,"exchange_name":"Binance","pair":"LINK/USDT","quote":{"currency_id":825,"currency_symbol":"USDT","currency_type":"cryptocurrency","exchange_symbol":"USDT"},"url":"https://www.binance.com/en/trade/LINK_USDT?ref=H31B921U"},{"base":{"currency_id":1975,"currency_symbol":"LINK","currency_type":"cryptocurrency","exchange_symbol":"LINK"},"exchange_id":300,"exchange_name":"BitZ","pair":"LINK/USDT","quote":{"currency_id":825,"currency_symbol":"USDT","currency_type":"cryptocurrency","exchange_symbol":"USDT"},"url":"https://www.bit-z.com/exchange/link_usdt"},{"base":{"currency_id":1975,"currency_symbol":"LINK","currency_type":"cryptocurrency","exchange_symbol":"LINK"},"exchange_id":89,"exchange_name":"Coinbase Pro","pair":"LINK/USD","quote":{"currency_id":2781,"currency_symbol":"USD","currency_type":"fiat","exchange_symbol":"USD"},"url":"https://pro.coinbase.com/trade/LINK-USD"},{"base":{"currency_id":1975,"currency_symbol":"LINK","currency_type":"cryptocurrency","exchange_symbol":"LINK"},"exchange_id":458,"exchange_name":"BBX","pair":"LINK/USDT","quote":{"currency_id":825,"currency_symbol":"USDT","currency_type":"cryptocurrency","exchange_symbol":"USDT"},"url":"https://bbx.com/exchange?coinPair=LINK/USDT"},{"base":{"currency_id":1975,"currency_symbol":"LINK","currency_type":"cryptocurrency","exchange_symbol":"LINK"},"exchange_id":270,"exchange_name":"Binance","pair":"LINK/BTC","quote":{"currency_id":1,"currency_symbol":"BTC","currency_type":"cryptocurrency","exchange_symbol":"BTC"},"url":"https://www.binance.com/en/trade/LINK_BTC?ref=H31B921U"},{"base":{"currency_id":1975,"currency_symbol":"LINK","currency_type":"cryptocurrency","exchange_symbol":"LINK"},"exchange_id":380,"exchange_name":"LATOKEN","pair":"LINK/BTC","quote":{"currency_id":1,"currency_symbol":"BTC","currency_type":"cryptocurrency","exchange_symbol":"BTC"},"url":"https://latoken.com/exchange/BTC-LINK"},{"base":{"currency_id":1975,"currency_symbol":"LINK","currency_type":"cryptocurrency","exchange_symbol":"LINK"},"exchange_id":407,"exchange_name":"DigiFinex","pair":"LINK/USDT","quote":{"currency_id":825,"currency_symbol":"USDT","currency_type":"cryptocurrency","exchange_symbol":"USDT"},"url":"https://www.digifinex.com/en-ww/trade/USDT/LINK"},{"base":{"currency_id":1975,"currency_symbol":"LINK","currency_type":"cryptocurrency","exchange_symbol":"LINK"},"exchange_id":102,"exchange_name":"Huobi Global","pair":"LINK/USDT","quote":{"currency_id":825,"currency_symbol":"USDT","currency_type":"cryptocurrency","exchange_symbol":"USDT"},"url":"https://www.hbg.com/en-us/exchange/link_usdt?invite_code=5kij5"},{"base":{"currency_id":1975,"currency_symbol":"LINK","currency_type":"cryptocurrency","exchange_symbol":"LINK"},"exchange_id":380,"exchange_name":"LATOKEN","pair":"LINK/ETH","quote":{"currency_id":1027,"currency_symbol":"ETH","currency_type":"cryptocurrency","exchange_symbol":"ETH"},"url":"https://latoken.com/exchange/ETH-LINK"},{"base":{"currency_id":1975,"currency_symbol":"LINK","currency_type":"cryptocurrency","exchange_symbol":"LINK"},"exchange_id":294,"exchange_name":"OKEx","pair":"LINK/USDT","quote":{"currency_id":825,"currency_symbol":"USDT","currency_type":"cryptocurrency","exchange_symbol":"USDT"},"url":"https://www.okex.com/market?product=link_usdt"},{"base":{"currency_id":1975,"currency_symbol":"LINK","currency_type":"cryptocurrency","exchange_symbol":"LINK"},"exchange_id":388,"exchange_name":"Sistemkoin","pair":"LINK/TRY","quote":{"currency_id":2810,"currency_symbol":"TRY","currency_type":"fiat","exchange_symbol":"TRY"},"url":"https://sistemkoin.com/#/"},{"base":{"currency_id":1975,"currency_symbol":"LINK","currency_type":"cryptocurrency","exchange_symbol":"LINK"},"exchange_id":673,"exchange_name":"UPEX","pair":"LINK/USDT","quote":{"currency_id":825,"currency_symbol":"USDT","currency_type":"cryptocurrency","exchange_symbol":"USDT"},"url":"https://upex.io/trade/LINK_USDT"},{"base":{"currency_id":1975,"currency_symbol":"LINK","currency_type":"cryptocurrency","exchange_symbol":"LINK"},"exchange_id":388,"exchange_name":"Sistemkoin","pair":"LINK/BTC","quote":{"currency_id":1,"currency_symbol":"BTC","currency_type":"cryptocurrency","exchange_symbol":"BTC"},"url":"https://sistemkoin.com/#/"},{"base":{"currency_id":1975,"currency_symbol":"LINK","currency_type":"cryptocurrency","exchange_symbol":"LINK"},"exchange_id":415,"exchange_name":"Bilaxy","pair":"LINK/USDT","quote":{"currency_id":825,"currency_symbol":"USDT","currency_type":"cryptocurrency","exchange_symbol":"USDT"},"url":"https://bilaxy.com/trade/LINK_USDT"},{"base":{"currency_id":1975,"currency_symbol":"LINK","currency_type":"cryptocurrency","exchange_symbol":"LINK"},"exchange_id":482,"exchange_name":"BKEX","pair":"LINK/USDT","quote":{"currency_id":825,"currency_symbol":"USDT","currency_type":"cryptocurrency","exchange_symbol":"USDT"},"url":"https://www.bkex.com/trade/LINK_USDT"},{"base":{"currency_id":1975,"currency_symbol":"LINK","currency_type":"cryptocurrency","exchange_symbol":"LINK"},"exchange_id":544,"exchange_name":"MXC","pair":"LINK/USDT","quote":{"currency_id":825,"currency_symbol":"USDT","currency_type":"cryptocurrency","exchange_symbol":"USDT"},"url":"https://www.mxc.com/trade/easy#LINK_USDT"},{"base":{"currency_id":1975,"currency_symbol":"LINK","currency_type":"cryptocurrency","exchange_symbol":"LINK"},"exchange_id":453,"exchange_name":"BitMax","pair":"LINK/USDT","quote":{"currency_id":825,"currency_symbol":"USDT","currency_type":"cryptocurrency","exchange_symbol":"USDT"},"url":"https://bitmax.io/#/trade/usdt/link"},{"base":{"currency_id":1975,"currency_symbol":"LINK","currency_type":"cryptocurrency","exchange_symbol":"LINK"},"exchange_id":388,"exchange_name":"Sistemkoin","pair":"LINK/USDT","quote":{"currency_id":825,"currency_symbol":"USDT","currency_type":"cryptocurrency","exchange_symbol":"USDT"},"url":"https://sistemkoin.com/#/"},{"base":{"currency_id":1975,"currency_symbol":"LINK","currency_type":"cryptocurrency","exchange_symbol":"LINK"},"exchange_id":380,"exchange_name":"LATOKEN","pair":"LINK/USDT","quote":{"currency_id":825,"currency_symbol":"USDT","currency_type":"cryptocurrency","exchange_symbol":"USDT"},"url":"https://latoken.com/exchange/USDT-LINK"},{"base":{"currency_id":1975,"currency_symbol":"LINK","currency_type":"cryptocurrency","exchange_symbol":"LINK"},"exchange_id":482,"exchange_name":"BKEX","pair":"LINK/ETH","quote":{"currency_id":1027,"currency_symbol":"ETH","currency_type":"cryptocurrency","exchange_symbol":"ETH"},"url":"https://www.bkex.com/trade/LINK_ETH"},{"base":{"currency_id":1975,"currency_symbol":"LINK","currency_type":"cryptocurrency","exchange_symbol":"LINK"},"exchange_id":398,"exchange_name":"DragonEX","pair":"LINK/USDT","quote":{"currency_id":825,"currency_symbol":"USDT","currency_type":"cryptocurrency","exchange_symbol":"USDT"},"url":"https://dragonex.io"},{"base":{"currency_id":1975,"currency_symbol":"LINK","currency_type":"cryptocurrency","exchange_symbol":"LINK"},"exchange_id":403,"exchange_name":"BitForex","pair":"LINK/ETH","quote":{"currency_id":1027,"currency_symbol":"ETH","currency_type":"cryptocurrency","exchange_symbol":"ETH"},"url":"https://www.bitforex.com/en/spot/link_eth"},{"base":{"currency_id":1975,"currency_symbol":"LINK","currency_type":"cryptocurrency","exchange_symbol":"LINK"},"exchange_id":339,"exchange_name":"Bibox","pair":"LINK/USDT","quote":{"currency_id":825,"currency_symbol":"USDT","currency_type":"cryptocurrency","exchange_symbol":"USDT"},"url":"https://www.bibox.com/exchange?coinPair=LINK_USDT"},{"base":{"currency_id":1975,"currency_symbol":"LINK","currency_type":"cryptocurrency","exchange_symbol":"LINK"},"exchange_id":388,"exchange_name":"Sistemkoin","pair":"LINK/ETH","quote":{"currency_id":1027,"currency_symbol":"ETH","currency_type":"cryptocurrency","exchange_symbol":"ETH"},"url":"https://sistemkoin.com/#/"},{"base":{"currency_id":1975,"currency_symbol":"LINK","currency_type":"cryptocurrency","exchange_symbol":"LINK"},"exchange_id":544,"exchange_name":"MXC","pair":"LINK/ETH","quote":{"currency_id":1027,"currency_symbol":"ETH","currency_type":"cryptocurrency","exchange_symbol":"ETH"},"url":"https://www.mxc.com/trade/easy#LINK_ETH"},{"base":{"currency_id":1975,"currency_symbol":"LINK","currency_type":"cryptocurrency","exchange_symbol":"LINK"},"exchange_id":487,"exchange_name":"VinDAX","pair":"LINK/USDT","quote":{"currency_id":825,"currency_symbol":"USDT","currency_type":"cryptocurrency","exchange_symbol":"USDT"},"url":"https://vindax.com/exchange-base.html?symbol=LINK_USDT"},{"base":{"currency_id":1975,"currency_symbol":"LINK","currency_type":"cryptocurrency","exchange_symbol":"LINK"},"exchange_id":487,"exchange_name":"VinDAX","pair":"LINK/ETH","quote":{"currency_id":1027,"currency_symbol":"ETH","currency_type":"cryptocurrency","exchange_symbol":"ETH"},"url":"https://vindax.com/exchange-base.html?symbol=LINK_ETH"},{"base":{"currency_id":1975,"currency_symbol":"LINK","currency_type":"cryptocurrency","exchange_symbol":"LINK"},"exchange_id":339,"exchange_name":"Bibox","pair":"LINK/BTC","quote":{"currency_id":1,"currency_symbol":"BTC","currency_type":"cryptocurrency","exchange_symbol":"BTC"},"url":"https://www.bibox.com/exchange?coinPair=LINK_BTC"},{"base":{"currency_id":1975,"currency_symbol":"LINK","currency_type":"cryptocurrency","exchange_symbol":"LINK"},"exchange_id":323,"exchange_name":"RightBTC","pair":"LINK/USDT","quote":{"currency_id":825,"currency_symbol":"USDT","currency_type":"cryptocurrency","exchange_symbol":"USDT"},"url":"https://www.rightbtc.com/trade/LINKUSDT"},{"base":{"currency_id":1975,"currency_symbol":"LINK","currency_type":"cryptocurrency","exchange_symbol":"LINK"},"exchange_id":343,"exchange_name":"CoinBene","pair":"LINK/BTC","quote":{"currency_id":1,"currency_symbol":"BTC","currency_type":"cryptocurrency","exchange_symbol":"BTC"},"url":"https://www.coinbene.com/exchange.html#/exchange?pairId=LINKBTC?hash=2NbmTq6"},{"base":{"currency_id":1975,"currency_symbol":"LINK","currency_type":"cryptocurrency","exchange_symbol":"LINK"},"exchange_id":406,"exchange_name":"BitMart","pair":"LINK/USDT","quote":{"currency_id":825,"currency_symbol":"USDT","currency_type":"cryptocurrency","exchange_symbol":"USDT"},"url":"https://www.bitmart.com/trade?symbol=LINK_USDT"},{"base":{"currency_id":1975,"currency_symbol":"LINK","currency_type":"cryptocurrency","exchange_symbol":"LINK"},"exchange_id":350,"exchange_name":"CoinEx","pair":"LINK/BTC","quote":{"currency_id":1,"currency_symbol":"BTC","currency_type":"cryptocurrency","exchange_symbol":"BTC"},"url":"https://www.coinex.com/trading?currency=btc&dest=link&tab=limit"},{"base":{"currency_id":1975,"currency_symbol":"LINK","currency_type":"cryptocurrency","exchange_symbol":"LINK"},"exchange_id":406,"exchange_name":"BitMart","pair":"LINK/BTC","quote":{"currency_id":1,"currency_symbol":"BTC","currency_type":"cryptocurrency","exchange_symbol":"BTC"},"url":"https://www.bitmart.com/trade?symbol=LINK_BTC"},{"base":{"currency_id":1975,"currency_symbol":"LINK","currency_type":"cryptocurrency","exchange_symbol":"LINK"},"exchange_id":294,"exchange_name":"OKEx","pair":"LINK/BTC","quote":{"currency_id":1,"currency_symbol":"BTC","currency_type":"cryptocurrency","exchange_symbol":"BTC"},"url":"https://www.okex.com/market?product=link_btc"},{"base":{"currency_id":1975,"currency_symbol":"LINK","currency_type":"cryptocurrency","exchange_symbol":"LINK"},"exchange_id":587,"exchange_name":"IndoEx","pair":"LINK/BTC","quote":{"currency_id":1,"currency_symbol":"BTC","currency_type":"cryptocurrency","exchange_symbol":"BTC"},"url":"https://international.indoex.io/trade/LINK_BTC"},{"base":{"currency_id":1975,"currency_symbol":"LINK","currency_type":"cryptocurrency","exchange_symbol":"LINK"},"exchange_id":587,"exchange_name":"IndoEx","pair":"LINK/USDT","quote":{"currency_id":825,"currency_symbol":"USDT","currency_type":"cryptocurrency","exchange_symbol":"USDT"},"url":"https://international.indoex.io/trade/LINK_USDT"},{"base":{"currency_id":1975,"currency_symbol":"LINK","currency_type":"cryptocurrency","exchange_symbol":"LINK"},"exchange_id":406,"exchange_name":"BitMart","pair":"LINK/ETH","quote":{"currency_id":1027,"currency_symbol":"ETH","currency_type":"cryptocurrency","exchange_symbol":"ETH"},"url":"https://www.bitmart.com/trade?symbol=LINK_ETH"},{"base":{"currency_id":1975,"currency_symbol":"LINK","currency_type":"cryptocurrency","exchange_symbol":"LINK"},"exchange_id":587,"exchange_name":"IndoEx","pair":"LINK/ETH","quote":{"currency_id":1027,"currency_symbol":"ETH","currency_type":"cryptocurrency","exchange_symbol":"ETH"},"url":"https://international.indoex.io/trade/LINK_ETH"},{"base":{"currency_id":1975,"currency_symbol":"LINK","currency_type":"cryptocurrency","exchange_symbol":"LINK"},"exchange_id":24,"exchange_name":"Kraken","pair":"LINK/USD","quote":{"currency_id":2781,"currency_symbol":"USD","currency_type":"fiat","exchange_symbol":"USD"},"url":"https://trade.kraken.com/markets/kraken/link/usd"},{"base":{"currency_id":1975,"currency_symbol":"LINK","currency_type":"cryptocurrency","exchange_symbol":"LINK"},"exchange_id":200,"exchange_name":"Bithumb","pair":"LINK/KRW","quote":{"currency_id":2798,"currency_symbol":"KRW","currency_type":"fiat","exchange_symbol":"KRW"},"url":"https://www.bithumb.com/trade/order/LINKKRW"},{"base":{"currency_id":1975,"currency_symbol":"LINK","currency_type":"cryptocurrency","exchange_symbol":"LINK"},"exchange_id":350,"exchange_name":"CoinEx","pair":"LINK/ETH","quote":{"currency_id":1027,"currency_symbol":"ETH","currency_type":"cryptocurrency","exchange_symbol":"ETH"},"url":"https://www.coinex.com/trading?currency=eth&dest=link&tab=limit"},{"base":{"currency_id":1975,"currency_symbol":"LINK","currency_type":"cryptocurrency","exchange_symbol":"LINK"},"exchange_id":270,"exchange_name":"Binance","pair":"LINK/ETH","quote":{"currency_id":1027,"currency_symbol":"ETH","currency_type":"cryptocurrency","exchange_symbol":"ETH"},"url":"https://www.binance.com/en/trade/LINK_ETH?ref=H31B921U"},{"base":{"currency_id":1975,"currency_symbol":"LINK","currency_type":"cryptocurrency","exchange_symbol":"LINK"},"exchange_id":89,"exchange_name":"Coinbase Pro","pair":"LINK/ETH","quote":{"currency_id":1027,"currency_symbol":"ETH","currency_type":"cryptocurrency","exchange_symbol":"ETH"},"url":"https://pro.coinbase.com/trade/LINK-ETH"},{"base":{"currency_id":1975,"currency_symbol":"LINK","currency_type":"cryptocurrency","exchange_symbol":"LINK"},"exchange_id":350,"exchange_name":"CoinEx","pair":"LINK/USDT","quote":{"currency_id":825,"currency_symbol":"USDT","currency_type":"cryptocurrency","exchange_symbol":"USDT"},"url":"https://www.coinex.com/trading?currency=usdt&dest=link&tab=limit"},{"base":{"currency_id":1975,"currency_symbol":"LINK","currency_type":"cryptocurrency","exchange_symbol":"LINK"},"exchange_id":294,"exchange_name":"OKEx","pair":"LINK/ETH","quote":{"currency_id":1027,"currency_symbol":"ETH","currency_type":"cryptocurrency","exchange_symbol":"ETH"},"url":"https://www.okex.com/market?product=link_eth"},{"base":{"currency_id":1975,"currency_symbol":"LINK","currency_type":"cryptocurrency","exchange_symbol":"LINK"},"exchange_id":350,"exchange_name":"CoinEx","pair":"LINK/BCH","quote":{"currency_id":1831,"currency_symbol":"BCH","currency_type":"cryptocurrency","exchange_symbol":"BCH"},"url":"https://www.coinex.com/trading?currency=bch&dest=link&tab=limit"},{"base":{"currency_id":1975,"currency_symbol":"LINK","currency_type":"cryptocurrency","exchange_symbol":"LINK"},"exchange_id":154,"exchange_name":"Dex-Trade","pair":"LINK/USDT","quote":{"currency_id":825,"currency_symbol":"USDT","currency_type":"cryptocurrency","exchange_symbol":"USDT"},"url":"https://dex-trade.com/en?currencyIn=LINK&currencyTo=USDT"},{"base":{"currency_id":1975,"currency_symbol":"LINK","currency_type":"cryptocurrency","exchange_symbol":"LINK"},"exchange_id":495,"exchange_name":"Folgory","pair":"LINK/ETH","quote":{"currency_id":1027,"currency_symbol":"ETH","currency_type":"cryptocurrency","exchange_symbol":"ETH"},"url":"https://folgory.com/trade-crypto/LINK_ETH"},{"base":{"currency_id":1975,"currency_symbol":"LINK","currency_type":"cryptocurrency","exchange_symbol":"LINK"},"exchange_id":24,"exchange_name":"Kraken","pair":"LINK/EUR","quote":{"currency_id":2790,"currency_symbol":"EUR","currency_type":"fiat","exchange_symbol":"EUR"},"url":"https://trade.kraken.com/markets/kraken/link/eur"},{"base":{"currency_id":1975,"currency_symbol":"LINK","currency_type":"cryptocurrency","exchange_symbol":"LINK"},"exchange_id":243,"exchange_name":"BtcTurk | Pro","pair":"LINK/TRY","quote":{"currency_id":2810,"currency_symbol":"TRY","currency_type":"fiat","exchange_symbol":"TRY"},"url":"https://pro.btcturk.com/pro/al-sat/LINK_TRY"},{"base":{"currency_id":1975,"currency_symbol":"LINK","currency_type":"cryptocurrency","exchange_symbol":"LINK"},"exchange_id":339,"exchange_name":"Bibox","pair":"LINK/ETH","quote":{"currency_id":1027,"currency_symbol":"ETH","currency_type":"cryptocurrency","exchange_symbol":"ETH"},"url":"https://www.bibox.com/exchange?coinPair=LINK_ETH"},{"base":{"currency_id":1975,"currency_symbol":"LINK","currency_type":"cryptocurrency","exchange_symbol":"LINK"},"exchange_id":225,"exchange_name":"Paribu","pair":"LINK/TRY","quote":{"currency_id":2810,"currency_symbol":"TRY","currency_type":"fiat","exchange_symbol":"TRY"},"url":"https://www.paribu.com/"},{"base":{"currency_id":1975,"currency_symbol":"LINK","currency_type":"cryptocurrency","exchange_symbol":"LINK"},"exchange_id":723,"exchange_name":"Rekeningku.com","pair":"LINK/IDR","quote":{"currency_id":2794,"currency_symbol":"IDR","currency_type":"fiat","exchange_symbol":"IDR"},"url":"https://www.rekeningku.com/trade/LINK-IDR"},{"base":{"currency_id":1975,"currency_symbol":"LINK","currency_type":"cryptocurrency","exchange_symbol":"LINK"},"exchange_id":468,"exchange_name":"OceanEx","pair":"LINK/USDT","quote":{"currency_id":825,"currency_symbol":"USDT","currency_type":"cryptocurrency","exchange_symbol":"USDT"},"url":"https://oceanex.pro/trades/linkusdt?referral=GNWJRA&linkId=24150518"},{"base":{"currency_id":1975,"currency_symbol":"LINK","currency_type":"cryptocurrency","exchange_symbol":"LINK"},"exchange_id":102,"exchange_name":"Huobi Global","pair":"LINK/BTC","quote":{"currency_id":1,"currency_symbol":"BTC","currency_type":"cryptocurrency","exchange_symbol":"BTC"},"url":"https://www.hbg.com/en-us/exchange/link_btc?invite_code=5kij5"},{"base":{"currency_id":1975,"currency_symbol":"LINK","currency_type":"cryptocurrency","exchange_symbol":"LINK"},"exchange_id":433,"exchange_name":"Bitrue","pair":"LINK/ETH","quote":{"currency_id":1027,"currency_symbol":"ETH","currency_type":"cryptocurrency","exchange_symbol":"ETH"},"url":"https://www.bitrue.com/trade/link_eth?inviteCode=VQQLQV"},{"base":{"currency_id":1975,"currency_symbol":"LINK","currency_type":"cryptocurrency","exchange_symbol":"LINK"},"exchange_id":483,"exchange_name":"Hanbitco","pair":"LINK/BTC","quote":{"currency_id":1,"currency_symbol":"BTC","currency_type":"cryptocurrency","exchange_symbol":"BTC"},"url":"https://www.hanbitco.com/exchange-basic/link_btc"},{"base":{"currency_id":1975,"currency_symbol":"LINK","currency_type":"cryptocurrency","exchange_symbol":"LINK"},"exchange_id":630,"exchange_name":"Binance.US","pair":"LINK/USD","quote":{"currency_id":2781,"currency_symbol":"USD","currency_type":"fiat","exchange_symbol":"USD"},"url":"https://www.binance.us/en/trade/LINK_USD"},{"base":{"currency_id":1975,"currency_symbol":"LINK","currency_type":"cryptocurrency","exchange_symbol":"LINK"},"exchange_id":270,"exchange_name":"Binance","pair":"LINK/USDC","quote":{"currency_id":3408,"currency_symbol":"USDC","currency_type":"cryptocurrency","exchange_symbol":"USDC"},"url":"https://www.binance.com/en/trade/LINK_USDC?ref=H31B921U"},{"base":{"currency_id":1975,"currency_symbol":"LINK","currency_type":"cryptocurrency","exchange_symbol":"LINK"},"exchange_id":473,"exchange_name":"Hubi","pair":"LINK/BTC","quote":{"currency_id":1,"currency_symbol":"BTC","currency_type":"cryptocurrency","exchange_symbol":"BTC"},"url":"https://www.hubi.com/#/exchange/link_btc"},{"base":{"currency_id":1975,"currency_symbol":"LINK","currency_type":"cryptocurrency","exchange_symbol":"LINK"},"exchange_id":673,"exchange_name":"UPEX","pair":"LINK/BTC","quote":{"currency_id":1,"currency_symbol":"BTC","currency_type":"cryptocurrency","exchange_symbol":"BTC"},"url":"https://upex.io/trade/LINK_BTC"},{"base":{"currency_id":1975,"currency_symbol":"LINK","currency_type":"cryptocurrency","exchange_symbol":"LINK"},"exchange_id":453,"exchange_name":"BitMax","pair":"LINK/BTC","quote":{"currency_id":1,"currency_symbol":"BTC","currency_type":"cryptocurrency","exchange_symbol":"BTC"},"url":"https://bitmax.io/#/trade/btc/link"},{"base":{"currency_id":1975,"currency_symbol":"LINK","currency_type":"cryptocurrency","exchange_symbol":"LINK"},"exchange_id":480,"exchange_name":"Cat.Ex","pair":"LINK/BTC","quote":{"currency_id":1,"currency_symbol":"BTC","currency_type":"cryptocurrency","exchange_symbol":"BTC"},"url":"https://www.catex.io/trading/LINK/BTC"},{"base":{"currency_id":1975,"currency_symbol":"LINK","currency_type":"cryptocurrency","exchange_symbol":"LINK"},"exchange_id":656,"exchange_name":"Omgfin","pair":"LINK/ETH","quote":{"currency_id":1027,"currency_symbol":"ETH","currency_type":"cryptocurrency","exchange_symbol":"ETH"},"url":"https://omgfin.com/exchange/trade/market/LINKETH"},{"base":{"currency_id":1975,"currency_symbol":"LINK","currency_type":"cryptocurrency","exchange_symbol":"LINK"},"exchange_id":468,"exchange_name":"OceanEx","pair":"LINK/VET","quote":{"currency_id":3077,"currency_symbol":"VET","currency_type":"cryptocurrency","exchange_symbol":"VET"},"url":"https://oceanex.pro/trades/linkvet?referral=GNWJRA&linkId=24150518"},{"base":{"currency_id":1975,"currency_symbol":"LINK","currency_type":"cryptocurrency","exchange_symbol":"LINK"},"exchange_id":24,"exchange_name":"Kraken","pair":"LINK/BTC","quote":{"currency_id":1,"currency_symbol":"BTC","currency_type":"cryptocurrency","exchange_symbol":"BTC"},"url":"https://trade.kraken.com/markets/kraken/link/btc"},{"base":{"currency_id":1975,"currency_symbol":"LINK","currency_type":"cryptocurrency","exchange_symbol":"LINK"},"exchange_id":730,"exchange_name":"Huobi Russia","pair":"LINK/USDT","quote":{"currency_id":825,"currency_symbol":"USDT","currency_type":"cryptocurrency","exchange_symbol":"USDT"},"url":"https://www.huobi.com.ru/exchange/#s=link_usdt"},{"base":{"currency_id":1975,"currency_symbol":"LINK","currency_type":"cryptocurrency","exchange_symbol":"LINK"},"exchange_id":487,"exchange_name":"VinDAX","pair":"LINK/BTC","quote":{"currency_id":1,"currency_symbol":"BTC","currency_type":"cryptocurrency","exchange_symbol":"BTC"},"url":"https://vindax.com/exchange-base.html?symbol=LINK_BTC"},{"base":{"currency_id":1975,"currency_symbol":"LINK","currency_type":"cryptocurrency","exchange_symbol":"LINK"},"exchange_id":853,"exchange_name":"AAX","pair":"LINK/BTC","quote":{"currency_id":1,"currency_symbol":"BTC","currency_type":"cryptocurrency","exchange_symbol":"BTC"},"url":"https://www.aax.com/spot/trade/LINK:BTC"},{"base":{"currency_id":1975,"currency_symbol":"LINK","currency_type":"cryptocurrency","exchange_symbol":"LINK"},"exchange_id":433,"exchange_name":"Bitrue","pair":"LINK/BTC","quote":{"currency_id":1,"currency_symbol":"BTC","currency_type":"cryptocurrency","exchange_symbol":"BTC"},"url":"https://www.bitrue.com/trade/link_btc?inviteCode=VQQLQV"},{"base":{"currency_id":1975,"currency_symbol":"LINK","currency_type":"cryptocurrency","exchange_symbol":"LINK"},"exchange_id":480,"exchange_name":"Cat.Ex","pair":"LINK/ETH","quote":{"currency_id":1027,"currency_symbol":"ETH","currency_type":"cryptocurrency","exchange_symbol":"ETH"},"url":"https://www.catex.io/trading/LINK/ETH"},{"base":{"currency_id":1975,"currency_symbol":"LINK","currency_type":"cryptocurrency","exchange_symbol":"LINK"},"exchange_id":154,"exchange_name":"Dex-Trade","pair":"LINK/BTC","quote":{"currency_id":1,"currency_symbol":"BTC","currency_type":"cryptocurrency","exchange_symbol":"BTC"},"url":"https://dex-trade.com/en?currencyIn=LINK&currencyTo=BTC"},{"base":{"currency_id":1975,"currency_symbol":"LINK","currency_type":"cryptocurrency","exchange_symbol":"LINK"},"exchange_id":528,"exchange_name":"BiKi","pair":"LINK/USDT","quote":{"currency_id":825,"currency_symbol":"USDT","currency_type":"cryptocurrency","exchange_symbol":"USDT"},"url":"https://www.biki.cc/en_US/trade/LINK_USDT"},{"base":{"currency_id":1975,"currency_symbol":"LINK","currency_type":"cryptocurrency","exchange_symbol":"LINK"},"exchange_id":587,"exchange_name":"IndoEx","pair":"LINK/USD","quote":{"currency_id":2781,"currency_symbol":"USD","currency_type":"fiat","exchange_symbol":"USD"},"url":"https://international.indoex.io/trade/LINK_USD"},{"base":{"currency_id":1975,"currency_symbol":"LINK","currency_type":"cryptocurrency","exchange_symbol":"LINK"},"exchange_id":853,"exchange_name":"AAX","pair":"LINK/USDT","quote":{"currency_id":825,"currency_symbol":"USDT","currency_type":"cryptocurrency","exchange_symbol":"USDT"},"url":"https://www.aax.com/spot/trade/LINK:USDT"},{"base":{"currency_id":1975,"currency_symbol":"LINK","currency_type":"cryptocurrency","exchange_symbol":"LINK"},"exchange_id":587,"exchange_name":"IndoEx","pair":"LINK/EUR","quote":{"currency_id":2790,"currency_symbol":"EUR","currency_type":"fiat","exchange_symbol":"EUR"},"url":"https://international.indoex.io/trade/LINK_EUR"},{"base":{"currency_id":1975,"currency_symbol":"LINK","currency_type":"cryptocurrency","exchange_symbol":"LINK"},"exchange_id":549,"exchange_name":"CITEX","pair":"LINK/USDT","quote":{"currency_id":825,"currency_symbol":"USDT","currency_type":"cryptocurrency","exchange_symbol":"USDT"},"url":"https://trade.citex.co.kr/trade/LINK_USDT"},{"base":{"currency_id":1975,"currency_symbol":"LINK","currency_type":"cryptocurrency","exchange_symbol":"LINK"},"exchange_id":549,"exchange_name":"CITEX","pair":"LINK/BTC","quote":{"currency_id":1,"currency_symbol":"BTC","currency_type":"cryptocurrency","exchange_symbol":"BTC"},"url":"https://trade.citex.co.kr/trade/LINK_BTC"},{"base":{"currency_id":1975,"currency_symbol":"LINK","currency_type":"cryptocurrency","exchange_symbol":"LINK"},"exchange_id":404,"exchange_name":"Kyber Network","pair":"LINK/ETH","quote":{"currency_id":1027,"currency_symbol":"ETH","currency_type":"cryptocurrency","exchange_symbol":"ETH"},"url":"https://kyberswap.com/swap/link-eth"},{"base":{"currency_id":1975,"currency_symbol":"LINK","currency_type":"cryptocurrency","exchange_symbol":"LINK"},"exchange_id":587,"exchange_name":"IndoEx","pair":"LINK/BSV","quote":{"currency_id":3602,"currency_symbol":"BSV","currency_type":"cryptocurrency","exchange_symbol":"BSV"},"url":"https://international.indoex.io/trade/LINK_BSV"},{"base":{"currency_id":1975,"currency_symbol":"LINK","currency_type":"cryptocurrency","exchange_symbol":"LINK"},"exchange_id":542,"exchange_name":"Bitsonic","pair":"LINK/KRW","quote":{"currency_id":2798,"currency_symbol":"KRW","currency_type":"fiat","exchange_symbol":"KRW"},"url":"https://bitsonic.co.kr/front/exchange/link-krw"},{"base":{"currency_id":1975,"currency_symbol":"LINK","currency_type":"cryptocurrency","exchange_symbol":"LINK"},"exchange_id":890,"exchange_name":"Bitay","pair":"LINK/TRY","quote":{"currency_id":2810,"currency_symbol":"TRY","currency_type":"fiat","exchange_symbol":"TRY"},"url":"https://www.bitay.com/en/t/LINKTRY"},{"base":{"currency_id":1975,"currency_symbol":"LINK","currency_type":"cryptocurrency","exchange_symbol":"LINK"},"exchange_id":151,"exchange_name":"Gemini","pair":"LINK/USD","quote":{"currency_id":2781,"currency_symbol":"USD","currency_type":"fiat","exchange_symbol":"USD"},"url":"https://gemini.com/"},{"base":{"currency_id":1975,"currency_symbol":"LINK","currency_type":"cryptocurrency","exchange_symbol":"LINK"},"exchange_id":270,"exchange_name":"Binance","pair":"LINK/BUSD","quote":{"currency_id":4687,"currency_symbol":"BUSD","currency_type":"cryptocurrency","exchange_symbol":"BUSD"},"url":"https://www.binance.com/en/trade/LINK_BUSD?ref=H31B921U"},{"base":{"currency_id":1975,"currency_symbol":"LINK","currency_type":"cryptocurrency","exchange_symbol":"LINK"},"exchange_id":323,"exchange_name":"RightBTC","pair":"LINK/BTC","quote":{"currency_id":1,"currency_symbol":"BTC","currency_type":"cryptocurrency","exchange_symbol":"BTC"},"url":"https://www.rightbtc.com/trade/LINKBTC"},{"base":{"currency_id":1975,"currency_symbol":"LINK","currency_type":"cryptocurrency","exchange_symbol":"LINK"},"exchange_id":495,"exchange_name":"Folgory","pair":"LINK/BTC","quote":{"currency_id":1,"currency_symbol":"BTC","currency_type":"cryptocurrency","exchange_symbol":"BTC"},"url":"https://folgory.com/trade-crypto/LINK_BTC"},{"base":{"currency_id":1975,"currency_symbol":"LINK","currency_type":"cryptocurrency","exchange_symbol":"LINK"},"exchange_id":213,"exchange_name":"Mercatox","pair":"LINK/BTC","quote":{"currency_id":1,"currency_symbol":"BTC","currency_type":"cryptocurrency","exchange_symbol":"BTC"},"url":"https://mercatox.com/exchange/LINK/BTC"},{"base":{"currency_id":1975,"currency_symbol":"LINK","currency_type":"cryptocurrency","exchange_symbol":"LINK"},"exchange_id":733,"exchange_name":"VCC Exchange","pair":"LINK/BTC","quote":{"currency_id":1,"currency_symbol":"BTC","currency_type":"cryptocurrency","exchange_symbol":"BTC"},"url":"https://vcc.exchange/exchange/basic?currency=btc&coin=link"},{"base":{"currency_id":1975,"currency_symbol":"LINK","currency_type":"cryptocurrency","exchange_symbol":"LINK"},"exchange_id":22,"exchange_name":"Bittrex","pair":"LINK/BTC","quote":{"currency_id":1,"currency_symbol":"BTC","currency_type":"cryptocurrency","exchange_symbol":"BTC"},"url":"https://bittrex.com/Market/Index?MarketName=BTC-LINK"},{"base":{"currency_id":1975,"currency_symbol":"LINK","currency_type":"cryptocurrency","exchange_symbol":"LINK"},"exchange_id":102,"exchange_name":"Huobi Global","pair":"LINK/ETH","quote":{"currency_id":1027,"currency_symbol":"ETH","currency_type":"cryptocurrency","exchange_symbol":"ETH"},"url":"https://www.hbg.com/en-us/exchange/link_eth?invite_code=5kij5"},{"base":{"currency_id":1975,"currency_symbol":"LINK","currency_type":"cryptocurrency","exchange_symbol":"LINK"},"exchange_id":613,"exchange_name":"Bitvast","pair":"LINK/USDC","quote":{"currency_id":3408,"currency_symbol":"USDC","currency_type":"cryptocurrency","exchange_symbol":"USDC"},"url":"https://trade.bitvast.com/trading/linkusdc"},{"base":{"currency_id":1975,"currency_symbol":"LINK","currency_type":"cryptocurrency","exchange_symbol":"LINK"},"exchange_id":355,"exchange_name":"Vebitcoin","pair":"LINK/TRY","quote":{"currency_id":2810,"currency_symbol":"TRY","currency_type":"fiat","exchange_symbol":"TRY"},"url":"https://www.vebitcoin.com/"},{"base":{"currency_id":1975,"currency_symbol":"LINK","currency_type":"cryptocurrency","exchange_symbol":"LINK"},"exchange_id":243,"exchange_name":"BtcTurk | Pro","pair":"LINK/USDT","quote":{"currency_id":825,"currency_symbol":"USDT","currency_type":"cryptocurrency","exchange_symbol":"USDT"},"url":"https://pro.btcturk.com/pro/al-sat/LINK_USDT"},{"base":{"currency_id":1975,"currency_symbol":"LINK","currency_type":"cryptocurrency","exchange_symbol":"LINK"},"exchange_id":213,"exchange_name":"Mercatox","pair":"LINK/ETH","quote":{"currency_id":1027,"currency_symbol":"ETH","currency_type":"cryptocurrency","exchange_symbol":"ETH"},"url":"https://mercatox.com/exchange/LINK/ETH"},{"base":{"currency_id":1975,"currency_symbol":"LINK","currency_type":"cryptocurrency","exchange_symbol":"LINK"},"exchange_id":495,"exchange_name":"Folgory","pair":"LINK/USDT","quote":{"currency_id":825,"currency_symbol":"USDT","currency_type":"cryptocurrency","exchange_symbol":"USDT"},"url":"https://folgory.com/trade-crypto/LINK_USDT"},{"base":{"currency_id":1975,"currency_symbol":"LINK","currency_type":"cryptocurrency","exchange_symbol":"LINK"},"exchange_id":890,"exchange_name":"Bitay","pair":"LINK/USDT","quote":{"currency_id":825,"currency_symbol":"USDT","currency_type":"cryptocurrency","exchange_symbol":"USDT"},"url":"https://www.bitay.com/en/t/LINKUSDT"},{"base":{"currency_id":1975,"currency_symbol":"LINK","currency_type":"cryptocurrency","exchange_symbol":"LINK"},"exchange_id":477,"exchange_name":"ProBit Exchange","pair":"LINK/USDT","quote":{"currency_id":825,"currency_symbol":"USDT","currency_type":"cryptocurrency","exchange_symbol":"USDT"},"url":"https://www.probit.com/app/exchange/LINK-USDT"}],"name":"Chainlink","rank":13,"slug":"chainlink","status":"active","symbol":"LINK"}