{"address":"0x6467882316dc6e206feef05fba6deaa69277f155","id":2118,"links":{"Chat":"https://t.me/FAPcoin_Crypto","Explorer":"https://etherscan.io/token/0x6467882316dc6e206feef05fba6deaa69277f155","Explorer 2":"https://ethplorer.io/address/0x6467882316dc6e206feef05fba6deaa69277f155","Twitter":"https://twitter.com/FAPcoin_Crypto","Website":"http://fapcoin.io/"},"markets":[{"exchange_name":"CoinExchange","pair":"FAP/BTC","url":"https://www.coinexchange.io/market/FAP/BTC"}],"name":"FAPcoin","symbol":"FAP","website_slug":"fapcoin"}