{"address":"0x66BaD545596fb17a0B4ebDC003a85dEF10E8F6Ae","category":"token","date_added":"2018-08-07T00:00:00.000Z","id":3090,"links":{"announcement":["https://bitcointalk.org/index.php?topic=2709833.0"],"explorer":["https://etherscan.io/token/0x66bad545596fb17a0b4ebdc003a85def10e8f6ae","https://etherscan.io/address/0x66bad545596fb17a0b4ebdc003a85def10e8f6ae"],"reddit":["https://reddit.com/r/WikiToken"],"twitter":["https://twitter.com/wiki_token"],"website":["https://wikitoken.bitcoinwiki.org"]},"markets":[{"base":{"currency_id":3090,"currency_symbol":"WIKI","currency_type":"cryptocurrency","exchange_symbol":"WIKI"},"exchange_id":42,"exchange_name":"HitBTC","pair":"WIKI/ETH","quote":{"currency_id":1027,"currency_symbol":"ETH","currency_type":"cryptocurrency","exchange_symbol":"ETH"},"url":"https://hitbtc.com/WIKI-to-ETH"},{"base":{"currency_id":3090,"currency_symbol":"WIKI","currency_type":"cryptocurrency","exchange_symbol":"WIKI"},"exchange_id":42,"exchange_name":"HitBTC","pair":"WIKI/USDT","quote":{"currency_id":825,"currency_symbol":"USDT","currency_type":"cryptocurrency","exchange_symbol":"USDT"},"url":"https://hitbtc.com/WIKI-to-USDT"},{"base":{"currency_id":3090,"currency_symbol":"WIKI","currency_type":"cryptocurrency","exchange_symbol":"WIKI"},"exchange_id":42,"exchange_name":"HitBTC","pair":"WIKI/BTC","quote":{"currency_id":1,"currency_symbol":"BTC","currency_type":"cryptocurrency","exchange_symbol":"BTC"},"url":"https://hitbtc.com/WIKI-to-BTC"}],"name":"Wiki Token","rank":2591,"slug":"wiki-token","status":"active","symbol":"WIKI"}