{"address":"0x6710CeE627Fa3A988200ffD5687cc1C814cEf0F6","category":"token","date_added":"2019-11-25T00:00:00.000Z","description":"Fortem Capital aims to tokenize real estate by allowing investors to invest in the property by using the Fortem Capital token.","id":4907,"links":{"announcement":["https://bitcointalk.org/index.php?topic=5157838.0"],"chat":["https://t.me/fortemcapital"],"explorer":["https://etherscan.io/token/0x6710cee627fa3a988200ffd5687cc1c814cef0f6","https://ethplorer.io/address/0x6710cee627fa3a988200ffd5687cc1c814cef0f6"],"message_board":["https://medium.com/@CapitalFortem"],"technical_doc":["https://fortemcoin.io/assets/doc/ENG_Whitepaper.pdf"],"twitter":["https://twitter.com/capitalFortem"],"website":["https://fortemcoin.io/"]},"name":"Fortem Capital","slug":"fortem-capital","status":"untracked","symbol":"FCQ"}