{"address":"0x7F86C782EC802ac402e0369d2E6d500256F7abC5","category":"coin","date_added":"2020-06-26T00:00:00.000Z","description":"RING X PLATFORM (RINGX) is a cryptocurrency. RING X PLATFORM has a current supply of 500,000,000 with ? in circulation. The last known price of RING X PLATFORM is $0.484340 USD and is down -2.25% over the last 24 hours. It is currently trading on 1 active market(s) with $29,342.53 traded over the last 24 hours. More information can be found at http://ringx.io/.","id":4894,"links":{"chat":["https://t.me/ringplat"],"explorer":["https://etherscan.io/token/0x7f86c782ec802ac402e0369d2e6d500256f7abc5","https://ethplorer.io/address/0x7f86c782ec802ac402e0369d2e6d500256f7abc5"],"message_board":["https://medium.com/@ringplatform"],"technical_doc":["http://ringx.io/RINGX_Platform_WHITE_PAPER_Ver_1_2_2.pdf"],"twitter":["https://twitter.com/PlatformRing"],"website":["http://ringx.io/"]},"markets":[{"base":{"currency_id":4894,"currency_symbol":"RINGX","currency_type":"cryptocurrency","exchange_symbol":"RINGX"},"exchange_id":37,"exchange_name":"Bitfinex","pair":"RINGX/USD","quote":{"currency_id":2781,"currency_symbol":"USD","currency_type":"fiat","exchange_symbol":"USD"},"url":"https://www.bitfinex.com/t/RINGX:USD?refcode=H70YTMupQ"}],"name":"RING X PLATFORM","rank":2320,"slug":"ring-x-platform","status":"active","symbol":"RINGX"}