{"address":"0x82b0e50478eeafde392d45d1259ed1071b6fda81","id":2208,"links":{"Announcement":"https://bitcointalk.org/index.php?topic=1968128.0","Chat":"https://gene-chain.slack.com/threads/","Explorer":"https://etherscan.io/token/0x82b0e50478eeafde392d45d1259ed1071b6fda81","Explorer 2":"https://etherscan.io/token/0x82b0e50478eeafde392d45d1259ed1071b6fda81","Reddit":"https://www.reddit.com/r/encrypgen","Technical Documentation":"https://icotimeline.com/wp-content/uploads/2017/07/Gene-Chain-Whitepaper.pdf","Twitter":"https://twitter.com/encrypgen","Website":"https://www.encrypgen.com/"},"markets":[{"exchange_name":"Coinbit","pair":"DNA/KRW","url":"https://www.coinbit.co.kr/trade/order/krw-dna"},{"exchange_name":"Cryptopia","pair":"DNA/BTC","url":"https://www.cryptopia.co.nz/Exchange?market=DNA_BTC"},{"exchange_name":"EtherDelta (ForkDelta)","pair":"DNA/ETH","url":"https://forkdelta.github.io/#!/trade/DNA-ETH"},{"exchange_name":"IDEX","pair":"DNA/ETH","url":"https://idex.market/eth/dna"},{"exchange_name":"OKEx","pair":"DNA/USDT","url":"https://www.okex.com/market?product=dna_usdt"}],"name":"EncrypGen","symbol":"DNA","website_slug":"encrypgen"}