{"address":"0xaEaabb69dcB0FE926B1979f0B032FCd17FD7b2E0","description":"The CYBR Ecosystem describes itself as a holistic cybersecurity solution for the blockchain that aims to secure smart transactions via real-time safeguards, countermeasures, and threat intelligence.\nThe CYBR Ecosystem describes itself as a holistic cybersecurity solution for the blockchain that aims to secure smart transactions via real-time safeguards, countermeasures, and threat intelligence.","id":4620,"links":{"Announcement":"https://bitcointalk.org/index.php?topic=5023957","Chat":"https://t.me/joinchat/IpnOJQ6irqRQU3RpE414lA","Explorer":"https://etherscan.io/token/0xaeaabb69dcb0fe926b1979f0b032fcd17fd7b2e0","Explorer 2":"https://ethplorer.io/address/0xaeaabb69dcb0fe926b1979f0b032fcd17fd7b2e0","Learn more":"/methodology/#rank","Message Board":"https://medium.com/cybrtoken","Source Code":"https://github.com/CYBRToken","Technical Documentation":"https://cybrtoken.io/wp-content/uploads/2019/05/CYBR_White-Paper.pdf","Twitter":"https://twitter.com/CYBR_Official?ref_src=coinmarketcap","Website":"https://cybrtoken.io/"},"markets":[{"exchange_name":"IDEX","pair":"CYBR/ETH","url":"https://idex.market/eth/cybr"},{"exchange_name":"OceanEx","pair":"CYBR/USDT","url":"https://oceanex.pro/trades/cybrusdt"}],"name":"CYBR Token","rank":1221,"symbol":"CYBR","tags":["Token"],"website_slug":"cybr-token"}