{"_DEPRECATED":true,"address":"0xB07ec2c28834B889b1CE527Ca0F19364cD38935c","id":2891,"links":{"chat":["https://telegram.me/cardstack"],"explorer":["https://etherscan.io/token/0xb07ec2c28834b889b1ce527ca0f19364cd38935c","https://ethplorer.io/address/0xb07ec2c28834b889b1ce527ca0f19364cd38935c"],"message_board":["https://medium.com/cardstack"],"source_code":["https://github.com/cardstack/cardstack"],"twitter":["https://twitter.com/cardstack"],"website":["https://cardstack.com/"]},"name":"Cardstack","slug":"cardstack","status":"deprecated","symbol":"CARD"}