{"_DEPRECATED":true,"address":"0xb92f51CE4045212EeF8008C2f665DA713035267B","id":3191,"links":{"Announcement":"https://bitcointalk.org/index.php?topic=4860767.0","Chat":"https://discordapp.com/invite/aXcUZeA","Explorer":"https://etherscan.io/token/0xb92f51ce4045212eef8008c2f665da713035267b","Explorer 2":"https://ethplorer.io/address/0xb92f51ce4045212eef8008c2f665da713035267b","Twitter":"https://twitter.com/rentledgerio","Website":"https://rentledger.io"},"markets":[{"exchange_name":"CoinExchange","pair":"RTL/BTC","url":"https://www.coinexchange.io/market/RTL/BTC"}],"name":"Rentledger","symbol":"RTL","website_slug":"rentledger"}