{"address":"0xcdcfc0f66c522fd086a1b725ea3c0eeb9f9e8814","id":2423,"links":{"Announcement":"https://bitcointalk.org/index.php?topic=2651604","Chat":"https://discord.gg/5vk6PTq","Explorer":"https://etherscan.io/token/0xcdcfc0f66c522fd086a1b725ea3c0eeb9f9e8814","Explorer 2":"https://ethplorer.io/address/0xcdcfc0f66c522fd086a1b725ea3c0eeb9f9e8814","Message Board":"https://medium.com/aurora-dao","Reddit":"https://www.reddit.com/r/auroradao","Twitter":"https://twitter.com/aurora_dao","Website":"https://auroradao.com"},"markets":[{"exchange_name":"IDEX","pair":"AURA/ETH","url":"https://idex.market/eth/aura"},{"exchange_name":"IDEX","pair":"AURA/TUSD","url":"https://idex.market/tusd/aura"}],"name":"Aurora DAO","symbol":"AURA","website_slug":"aurora-dao"}