{"_DEPRECATED":true,"address":"0xde2f7766c8bf14ca67193128535e5c7454f8387c","id":3418,"links":{"Chat":"https://t.me/MetadiumOfficial","Explorer":"https://etherscan.io/token/0xde2f7766c8bf14ca67193128535e5c7454f8387c","Explorer 2":"https://ethplorer.io/address/0xde2f7766c8bf14ca67193128535e5c7454f8387c","Message Board":"https://medium.com/metadium","Reddit":"https://www.reddit.com/r/metadiumprotocol","Source Code":"https://github.com/metadium","Technical Documentation":"https://www.metadium.com/whitepaper","Twitter":"https://twitter.com/metadium","Website":"https://www.metadium.com/"},"markets":[{"exchange_name":"ABCC","pair":"META/ETH","url":"https://abcc.com/markets/metaeth"},{"exchange_name":"Bittrex","pair":"META/BTC","url":"https://bittrex.com/Market/Index?MarketName=BTC-META"},{"exchange_name":"Bytex","pair":"META/BTC","url":"https://www.bytex.io/trade_center.html"},{"exchange_name":"Bytex","pair":"META/USDT","url":"https://www.bytex.io/trade_center.html"},{"exchange_name":"Coinsuper","pair":"META/ETH","url":"https://www.coinsuper.com/#/actionDeal"},{"exchange_name":"Hotbit","pair":"META/BTC","url":"https://www.hotbit.io/"},{"exchange_name":"Hotbit","pair":"META/ETH","url":"https://www.hotbit.io/"},{"exchange_name":"KuCoin","pair":"META/ETH","url":"https://www.kucoin.com/trade/META-ETH"},{"exchange_name":"Upbit","pair":"META/BTC","url":"https://upbit.com/exchange?code=CRIX.UPBIT.BTC-META"}],"name":"Metadium","symbol":"META","website_slug":"metadium"}