{"address":"0xE1Aee98495365fc179699C1bB3E761FA716beE62","description":"Bezant is a decentralized payment protocol that allows content creators and online merchants to setup stores and send/receive payments internationally. \nBezant is a decentralized payment protocol that allows content creators and online merchants to setup stores and send/receive payments internationally. \nThe BZNT ERC-20 token enables users to make purchases on the Jehmi platform and access global content. Its purported benefits include the elimination of costly store fees and the provision of instant P2P payments to merchants.\nThe BZNT ERC-20 token enables users to make purchases on the Jehmi platform and access global content. Its purported benefits include the elimination of costly store fees and the provision of instant P2P payments to merchants.","id":2727,"links":{"Announcement":"https://bitcointalk.org/index.php?topic=3290668.0","Explorer":"https://etherscan.io/token/0xe1aee98495365fc179699c1bb3e761fa716bee62","Explorer 2":"https://ethplorer.io/address/0xe1aee98495365fc179699c1bb3e761fa716bee62","Message Board":"https://medium.com/bezant","Reddit":"https://www.reddit.com/r/Bezant","Technical Documentation":"https://cdn.bezant.io/bezant/Bezant_WP.pdf","Twitter":"https://twitter.com/bezant_io?ref_src=coinmarketcap","Website":"https://bezant.io/"},"markets":[{"exchange_name":"Bibox","pair":"BZNT/ETH","url":"https://www.bibox.com/exchange?coinPair=BZNT_ETH"},{"exchange_name":"Bilaxy","pair":"BZNT/ETH","url":"https://bilaxy.com/exchange"},{"exchange_name":"Binance DEX","pair":"BZNT/BNB","url":"https://www.binance.org/en/trade/BZNT-464_BNB"},{"exchange_name":"Bithumb Global","pair":"BZNT/USDT","url":"https://www.bithumb.pro/en-us/spot/trade;symbol=BZNT_USDT"},{"exchange_name":"Bithumb Singapore","pair":"BZNT/BTC","url":"https://www.bithumbsg.com/exchange/bznt-btc"},{"exchange_name":"Bithumb","pair":"BZNT/KRW","url":"https://www.bithumb.com/"},{"exchange_name":"Dcoin","pair":"BZNT/ETH","url":"https://www.dcoin.com/currencyTrading/BZNT_ETH"},{"exchange_name":"Fatbtc","pair":"BZNT/ETH","url":"https://www.fatbtc.com/"},{"exchange_name":"Hotbit","pair":"BZNT/BTC","url":"https://www.hotbit.io/exchange?symbol=BZNT_BTC"},{"exchange_name":"Hotbit","pair":"BZNT/ETH","url":"https://www.hotbit.io/exchange?symbol=BZNT_ETH"},{"exchange_name":"IDEX","pair":"BZNT/ETH","url":"https://idex.market/eth/bznt"}],"name":"Bezant","rank":561,"symbol":"BZNT","tags":["Token"],"website_slug":"bezant"}