{"address":"0xf8e386eda857484f5a12e4b5daa9984e06e73705","id":1967,"links":{"Announcement":"https://bitcointalk.org/index.php?topic=2047503.0","Explorer":"https://etherscan.io/token/0xf8e386eda857484f5a12e4b5daa9984e06e73705","Explorer 2":"https://ethplorer.io/address/0xf8e386eda857484f5a12e4b5daa9984e06e73705","Reddit":"https://www.reddit.com/r/indorse","Technical Documentation":"https://indorse.io/static/media/Indorse-Whitepaper-v1.1.a733cc8e.pdf","Twitter":"https://twitter.com/joinindorse","Website":"https://indorse.io/"},"markets":[{"exchange_name":"Bancor Network","pair":"IND/BNT","url":"https://www.bancor.network/"},{"exchange_name":"COSS","pair":"IND/BTC","url":"https://exchange.coss.io/exchange/ind-btc"},{"exchange_name":"COSS","pair":"IND/ETH","url":"https://exchange.coss.io/exchange/ind-eth"},{"exchange_name":"DDEX","pair":"IND/ETH","url":"https://ddex.io/trade/IND-ETH"},{"exchange_name":"HitBTC","pair":"IND/ETH","url":"https://hitbtc.com/IND-to-ETH"},{"exchange_name":"IDEX","pair":"IND/ETH","url":"https://idex.market/eth/ind"},{"exchange_name":"Liqui","pair":"IND/BTC","url":"https://liqui.io/#/exchange/IND_BTC"},{"exchange_name":"Liqui","pair":"IND/ETH","url":"https://liqui.io/#/exchange/IND_ETH"},{"exchange_name":"Liqui","pair":"IND/USDT","url":"https://liqui.io/#/exchange/IND_USDT"},{"exchange_name":"RightBTC","pair":"IND/BTC","url":"https://www.rightbtc.com/"},{"exchange_name":"RightBTC","pair":"IND/ETH","url":"https://www.rightbtc.com/"},{"exchange_name":"RightBTC","pair":"IND/ETP","url":"https://www.rightbtc.com/"},{"exchange_name":"YoBit","pair":"IND/BTC","url":"https://yobit.net/en/trade/IND/BTC"}],"name":"Indorse Token","symbol":"IND","website_slug":"indorse-token"}